yepcode_run/__init__.py
yepcode_run/api/api_manager.py
yepcode_run/api/types.py
yepcode_run/api/yepcode_api.py
yepcode_run/env/yepcode_env.py
yepcode_run/run/execution.py
yepcode_run/run/yepcode_run.py
yepcode_run/storage/yepcode_storage.py
yepcode_run/types.py
yepcode_run/utils/__init__.py
yepcode_run/utils/config_manager.py
yepcode_run/utils/language_detector.py
yepcode_run-1.6.1.dist-info/LICENSE
yepcode_run-1.6.1.dist-info/METADATA
yepcode_run-1.6.1.dist-info/WHEEL
yepcode_run-1.6.1.dist-info/RECORD
