Metadata-Version: 2.3
Name: yepcode-run
Version: 1.6.1
Summary: YepCode Run - A powerful serverless runtime and SDK for executing code in secure sandboxes
License: See LICENSE file
Author: YepCode Developers
Author-email: developers@yepcode.io
Requires-Python: >=3.11,<4.0
Classifier: License :: Other/Proprietary License
Classifier: Programming Language :: Python :: 3
Classifier: Programming Language :: Python :: 3.11
Classifier: Programming Language :: Python :: 3.12
Classifier: Programming Language :: Python :: 3.13
Requires-Dist: python-dotenv (>=1.0.1,<2.0.0)
Requires-Dist: requests (>=2.32.3,<3.0.0)
Project-URL: Homepage, https://yepcode.io/run/
